{
  "measuredAt": "2026-06-10",
  "dims": "default H120/Rt70/Rb45",
  "bar": "clean-CAD min-angle>=20deg",
  "rows": [
    {
      "styleId": "SuperformulaBlossom",
      "triangleCount": 76544,
      "degenerateCount": 0,
      "minAngleDeg": 4.7,
      "p5MinAngleDeg": 16,
      "medianMinAngleDeg": 32,
      "meanMinAngleDeg": 30.9,
      "pctBelow10": 0.7,
      "pctBelow20": 17.2,
      "pctBelow30": 40.8,
      "buildMs": 4954
    },
    {
      "styleId": "FourierBloom",
      "triangleCount": 189514,
      "degenerateCount": 0,
      "minAngleDeg": 4.7,
      "p5MinAngleDeg": 15,
      "medianMinAngleDeg": 24,
      "meanMinAngleDeg": 27.2,
      "pctBelow10": 0.4,
      "pctBelow20": 24.8,
      "pctBelow30": 69.7,
      "buildMs": 9013
    },
    {
      "styleId": "SuperellipseMorph",
      "triangleCount": 113160,
      "degenerateCount": 0,
      "minAngleDeg": 4.7,
      "p5MinAngleDeg": 13,
      "medianMinAngleDeg": 24,
      "meanMinAngleDeg": 26.5,
      "pctBelow10": 0.5,
      "pctBelow20": 38.7,
      "pctBelow30": 61.4,
      "buildMs": 4967
    },
    {
      "styleId": "HarmonicRipple",
      "triangleCount": 212462,
      "degenerateCount": 0,
      "minAngleDeg": 4.6,
      "p5MinAngleDeg": 18,
      "medianMinAngleDeg": 34,
      "meanMinAngleDeg": 34.5,
      "pctBelow10": 1.5,
      "pctBelow20": 5.9,
      "pctBelow30": 26.4,
      "buildMs": 6330
    },
    {
      "styleId": "LowPolyFacet",
      "triangleCount": 111904,
      "degenerateCount": 0,
      "minAngleDeg": 3.1,
      "p5MinAngleDeg": 13,
      "medianMinAngleDeg": 28,
      "meanMinAngleDeg": 27.9,
      "pctBelow10": 0.5,
      "pctBelow20": 33.3,
      "pctBelow30": 56.9,
      "buildMs": 4276
    },
    {
      "styleId": "GothicArches",
      "triangleCount": 316560,
      "degenerateCount": 0,
      "minAngleDeg": 3.1,
      "p5MinAngleDeg": 11,
      "medianMinAngleDeg": 22,
      "meanMinAngleDeg": 23.2,
      "pctBelow10": 0.5,
      "pctBelow20": 42.1,
      "pctBelow30": 75.4,
      "buildMs": 12248
    },
    {
      "styleId": "WaveInterference",
      "triangleCount": 108108,
      "degenerateCount": 0,
      "minAngleDeg": 4.7,
      "p5MinAngleDeg": 16,
      "medianMinAngleDeg": 24,
      "meanMinAngleDeg": 28.1,
      "pctBelow10": 0.5,
      "pctBelow20": 28.4,
      "pctBelow30": 55.7,
      "buildMs": 5115
    },
    {
      "styleId": "Crystalline",
      "triangleCount": 397816,
      "degenerateCount": 0,
      "minAngleDeg": 1.4,
      "p5MinAngleDeg": 12,
      "medianMinAngleDeg": 22,
      "meanMinAngleDeg": 24.6,
      "pctBelow10": 3.1,
      "pctBelow20": 38.7,
      "pctBelow30": 73.7,
      "buildMs": 16172
    },
    {
      "styleId": "ArtDeco",
      "triangleCount": 277208,
      "degenerateCount": 0,
      "minAngleDeg": 3.7,
      "p5MinAngleDeg": 14,
      "medianMinAngleDeg": 20,
      "meanMinAngleDeg": 23.5,
      "pctBelow10": 4.7,
      "pctBelow20": 49,
      "pctBelow30": 74.7,
      "buildMs": 10047
    },
    {
      "styleId": "DragonScales",
      "triangleCount": 374172,
      "degenerateCount": 0,
      "minAngleDeg": 4.3,
      "p5MinAngleDeg": 13,
      "medianMinAngleDeg": 30,
      "meanMinAngleDeg": 30.5,
      "pctBelow10": 3,
      "pctBelow20": 13.3,
      "pctBelow30": 49.9,
      "buildMs": 17886
    },
    {
      "styleId": "BambooSegments",
      "triangleCount": 295270,
      "degenerateCount": 0,
      "minAngleDeg": 4.7,
      "p5MinAngleDeg": 13,
      "medianMinAngleDeg": 23,
      "meanMinAngleDeg": 25.6,
      "pctBelow10": 0.2,
      "pctBelow20": 39.1,
      "pctBelow30": 66.9,
      "buildMs": 11289
    },
    {
      "styleId": "RippleInterference",
      "triangleCount": 148824,
      "degenerateCount": 0,
      "minAngleDeg": 4.7,
      "p5MinAngleDeg": 16,
      "medianMinAngleDeg": 21,
      "meanMinAngleDeg": 25.7,
      "pctBelow10": 0.3,
      "pctBelow20": 40.6,
      "pctBelow30": 65.5,
      "buildMs": 6512
    },
    {
      "styleId": "GyroidManifold",
      "triangleCount": 324722,
      "degenerateCount": 0,
      "minAngleDeg": 2.1,
      "p5MinAngleDeg": 10,
      "medianMinAngleDeg": 19,
      "meanMinAngleDeg": 23,
      "pctBelow10": 4.7,
      "pctBelow20": 50.7,
      "pctBelow30": 77.4,
      "buildMs": 13583
    },
    {
      "styleId": "Voronoi",
      "triangleCount": 569126,
      "degenerateCount": 0,
      "minAngleDeg": 1.8,
      "p5MinAngleDeg": 15,
      "medianMinAngleDeg": 22,
      "meanMinAngleDeg": 26.8,
      "pctBelow10": 0.6,
      "pctBelow20": 36,
      "pctBelow30": 63.9,
      "buildMs": 21036
    },
    {
      "styleId": "BasketWeave",
      "triangleCount": 667614,
      "degenerateCount": 0,
      "minAngleDeg": 2.9,
      "p5MinAngleDeg": 11,
      "medianMinAngleDeg": 16,
      "meanMinAngleDeg": 20.3,
      "pctBelow10": 3.4,
      "pctBelow20": 68.6,
      "pctBelow30": 81.4,
      "buildMs": 25852
    },
    {
      "styleId": "GeometricStar",
      "triangleCount": 357200,
      "degenerateCount": 0,
      "minAngleDeg": 4.2,
      "p5MinAngleDeg": 12,
      "medianMinAngleDeg": 20,
      "meanMinAngleDeg": 23,
      "pctBelow10": 3.7,
      "pctBelow20": 47.9,
      "pctBelow30": 78.3,
      "buildMs": 13504
    },
    {
      "styleId": "HexagonalHive",
      "triangleCount": 283984,
      "degenerateCount": 0,
      "minAngleDeg": 1.4,
      "p5MinAngleDeg": 15,
      "medianMinAngleDeg": 19,
      "meanMinAngleDeg": 22.9,
      "pctBelow10": 0.7,
      "pctBelow20": 53.4,
      "pctBelow30": 80.4,
      "buildMs": 10169
    },
    {
      "styleId": "CelticKnot",
      "triangleCount": 355204,
      "degenerateCount": 0,
      "minAngleDeg": 2.5,
      "p5MinAngleDeg": 10,
      "medianMinAngleDeg": 20,
      "meanMinAngleDeg": 22.8,
      "pctBelow10": 4.5,
      "pctBelow20": 49.4,
      "pctBelow30": 77.8,
      "buildMs": 13791
    },
    {
      "styleId": "CelticTriquetra",
      "triangleCount": 1091442,
      "degenerateCount": 0,
      "minAngleDeg": 3.8,
      "p5MinAngleDeg": 13,
      "medianMinAngleDeg": 20,
      "meanMinAngleDeg": 24.4,
      "pctBelow10": 0.1,
      "pctBelow20": 46,
      "pctBelow30": 76.4,
      "buildMs": 47853
    },
    {
      "styleId": "SpiralRidges",
      "triangleCount": 221750,
      "degenerateCount": 0,
      "minAngleDeg": 2.4,
      "p5MinAngleDeg": 15,
      "medianMinAngleDeg": 36,
      "meanMinAngleDeg": 35.8,
      "pctBelow10": 2.4,
      "pctBelow20": 8.4,
      "pctBelow30": 27.6,
      "buildMs": 9618
    }
  ]
}